setup.py
gtchecker/Client.py
gtchecker/_init_.py
gtchecker/client.py
gtchecker/errors.py
gtchecker.egg-info/PKG-INFO
gtchecker.egg-info/SOURCES.txt
gtchecker.egg-info/dependency_links.txt
gtchecker.egg-info/top_level.txt