Metadata-Version: 1.1
Name: gtchecker
Version: 0.0.6
Summary: Official API Wrapper for Gtchecker.com
Home-page: https://gtchecker.com
Author: Joker
Author-email: abuse@gtchecker.com
License: MIT
Platform: UNKNOWN
Classifier: Programming Language :: Python :: 3
Classifier: Operating System :: OS Independent
